besos/examples/ExamplesOverview.ipynb
besos/examples/NotebookTest.ipynb
besos/examples/WelcomeToBESOS.ipynb
besos/examples/.ipynb_checkpoints/WelcomeToBESOS-checkpoint.ipynb
besos/examples/ClusterSubmission/ClusterSubmission.ipynb
besos/examples/ClusterSubmission/SFTP.ipynb
besos/examples/ClusterSubmission/TerminalTutorial.ipynb
besos/examples/ClusterSubmission/cluster.py
besos/examples/ClusterSubmission/clusterbatch.sh
besos/examples/ClusterSubmission/op.out
besos/examples/ClusterSubmission/parameter_sets.py
besos/examples/ClusterSubmission/time.cluster
besos/examples/DataAnalysis/BayesianNetwork.ipynb
besos/examples/DataAnalysis/Models_NaiveBayesianDistributions_22
besos/examples/DataAnalysis/Residential_22.csv
besos/examples/DataAnalysis/ecobee_public/AnalyzeModelResults.ipynb
besos/examples/DataAnalysis/ecobee_public/BalancePointVisualization.ipynb
besos/examples/DataAnalysis/ecobee_public/DecayCurvesVisualization.ipynb
besos/examples/DataAnalysis/ecobee_public/FittingGreyboxModels.ipynb
besos/examples/DataAnalysis/ecobee_public/ModelFittingVisualization.ipynb
besos/examples/DataAnalysis/ecobee_public/data/example_results_from_paper.csv
besos/examples/DataAnalysis/ecobee_public/data/model_results/balance_point.csv
besos/examples/DataAnalysis/ecobee_public/data/model_results/params.csv
besos/examples/DataAnalysis/ecobee_public/data/model_results/1/balance_point.csv
besos/examples/DataAnalysis/ecobee_public/data/model_results/1/params.csv
besos/examples/DataAnalysis/ecobee_public/data/model_results/1/decay_curves/0394b7ad85da211021eac434ac103b8289370ef4.csv
besos/examples/DataAnalysis/ecobee_public/data/model_results/1/decay_curves/a937d992bbae47858967713080c8e8173b331e9c.csv
besos/examples/DataAnalysis/ecobee_public/data/model_results/1/model_fitting/0394b7ad85da211021eac434ac103b8289370ef4.csv
besos/examples/DataAnalysis/ecobee_public/data/model_results/1/model_fitting/a937d992bbae47858967713080c8e8173b331e9c.csv
besos_examples-0.1.0.dist-info/METADATA
besos_examples-0.1.0.dist-info/WHEEL
besos_examples-0.1.0.dist-info/top_level.txt
besos_examples-0.1.0.dist-info/RECORD
