Metadata-Version: 2.1
Name: besos-examples
Version: 0.1.0
Summary: A collection of examples for the besos python package
Home-page: https://gitlab.com/energyincities/besos
Author: Ralph Evins
Author-email: besos@uvic.ca
Classifier: Programming Language :: Python :: 3
Classifier: License :: OSI Approved :: GNU General Public License (GPL)
Classifier: Operating System :: OS Independent
